setup.cfg
setup.py
my_second_module/__init__.py
my_second_module/exp_func.py
my_second_module.egg-info/PKG-INFO
my_second_module.egg-info/SOURCES.txt
my_second_module.egg-info/dependency_links.txt
my_second_module.egg-info/entry_points.txt
my_second_module.egg-info/not-zip-safe
my_second_module.egg-info/top_level.txt