Metadata-Version: 1.0
Name: my-second-module
Version: 1.0.dev0
Summary: module with math functions
Home-page: UNKNOWN
Author: UNKNOWN
Author-email: UNKNOWN
License: UNKNOWN
Platform: UNKNOWN
